opinum_api_connector/__init__.py
opinum_api_connector/utils/__init__.py
opinum_api_connector/utils/site_content_duplicator.py
opinum_api_connector-1.2.7.dist-info/licenses/LICENSE
opinum_api_connector-1.2.7.dist-info/METADATA
opinum_api_connector-1.2.7.dist-info/WHEEL
opinum_api_connector-1.2.7.dist-info/top_level.txt
opinum_api_connector-1.2.7.dist-info/RECORD
