Metadata-Version: 2.4
Name: opinum-api-connector
Version: 1.2.7
Summary: Package to interact with the Opinum API
Home-page: https://github.com/opinum/opinum-api-connector
Author: Opinum
Author-email: support@opinum.com
Classifier: Programming Language :: Python :: 3.6
Classifier: License :: OSI Approved :: MIT License
Classifier: Operating System :: OS Independent
Requires-Python: >=3.6
License-File: LICENSE
Requires-Dist: requests
Requires-Dist: requests_oauthlib
Requires-Dist: oauthlib
Dynamic: author
Dynamic: author-email
Dynamic: classifier
Dynamic: description
Dynamic: description-content-type
Dynamic: home-page
Dynamic: license-file
Dynamic: requires-dist
Dynamic: requires-python
Dynamic: summary
